[
  {
    "$type": "ModListMetadata, Wabbajack.Lib",
    "title": "Mages & Vikings",
    "description": "Some may call this junk. Me, I call this Mages & Vikings.",
    "author": "SEEYOULHATER",
    "maintainers": [
      "github/nicolasbertolino"
    ],
    "game": "skyrimspecialedition",
    "tags": [
      "Official",
      "High Fantasy",
      "SFW"
    ],
    "official": true,
    "nsfw": false,
    "image_contains_title": false,
    "force_down": false,
    "links": {
      "$type": "Links, Wabbajack.Lib",
      "image": "https://raw.githubusercontent.com/nicolasbertolino/MagesAndVikings/main/banner.webp",
      "readme": "https://github.com/nicolasbertolino/MagesAndVikings/blob/main/README.md",
      "download": "https://authored-files.wabbajack.org/Mages%20&%20Vikings.wabbajack_616e4fa5-a1e6-46c3-9e5f-66864536c340",
      "machineURL": "MagesAndVikings",
      "discordURL": "https://discord.gg/Newa3dj5pZ"
    },
    "download_metadata": {
      "$type": "DownloadMetadata, Wabbajack.Lib",
      "Hash": "njO/CImhSp8=",
      "Size": 669426972,
      "NumberOfArchives": 3236,
      "SizeOfArchives": 214176336423,
      "NumberOfInstalledFiles": 268989,
      "SizeOfInstalledFiles": 343661555997,
      "TotalSize": 557837892420
    },
    "version": "2.10.2"
  }
]
